dataclasses_hjson.py
dataclasses_hjson-0.0.3.dist-info/LICENSE
dataclasses_hjson-0.0.3.dist-info/METADATA
dataclasses_hjson-0.0.3.dist-info/WHEEL
dataclasses_hjson-0.0.3.dist-info/RECORD
