Metadata-Version: 2.1
Name: dataclasses-hjson
Version: 0.0.3
Summary: A simple mixin that adds .to_hjson and .from_hjson to the dataclasses-json mixin
Home-page: https://github.com/J0J0HA/dataclasses-hjson
License: MIT
Keywords: dataclasses,json,hjson
Author: J0J0HA
Author-email: johannes@jojojux.de
Requires-Python: >=3.7,<4.0
Classifier: License :: OSI Approved :: MIT License
Classifier: Programming Language :: Python :: 3
Classifier: Programming Language :: Python :: 3.7
Classifier: Programming Language :: Python :: 3.8
Classifier: Programming Language :: Python :: 3.9
Classifier: Programming Language :: Python :: 3.10
Classifier: Programming Language :: Python :: 3.11
Classifier: Programming Language :: Python :: 3.12
Requires-Dist: dataclasses-json (>=0.6.4,<0.7.0)
Project-URL: Repository, https://github.com/J0J0HA/dataclasses-hjson
